llm_metrics_lite/__init__.py
llm_metrics_lite/cli.py
llm_metrics_lite/coherence.py
llm_metrics_lite/cost.py
llm_metrics_lite/eval.py
llm_metrics_lite/factuality.py
llm_metrics_lite/latency.py
llm_metrics_lite/lexical.py
llm_metrics_lite/numeric.py
llm_metrics_lite/perplexity.py
llm_metrics_lite/quality.py
llm_metrics_lite/readability.py
llm_metrics_lite/repetition.py
llm_metrics_lite/tokens.py
llm_metrics_lite/uncertinity.py
llm_metrics_lite-0.2.3.dist-info/licenses/LICENSE
llm_metrics_lite-0.2.3.dist-info/METADATA
llm_metrics_lite-0.2.3.dist-info/WHEEL
llm_metrics_lite-0.2.3.dist-info/top_level.txt
llm_metrics_lite-0.2.3.dist-info/RECORD
