Metadata-Version: 2.4
Name: llm-metrics-lite
Version: 0.2.3
Summary: A lightweight evaluation framework for large language model outputs
Author-email: Supriya Bachal <supriyabachal@gmail.com>
License: MIT
Project-URL: Homepage, https://github.com/supriyabachal/llm_metrics_lite
Project-URL: Repository, https://github.com/supriyabachal/llm_metrics_lite
Project-URL: Issues, https://github.com/supriyabachal/llm_metrics_lite/issues
Project-URL: Documentation, https://pypi.org/project/llm-metrics-lite/
Keywords: LLM,evaluation,metrics,AI,NLP,coherence,perplexity
Classifier: Programming Language :: Python :: 3
Classifier: Programming Language :: Python :: 3 :: Only
Classifier: License :: OSI Approved :: MIT License
Classifier: Operating System :: OS Independent
Classifier: Topic :: Scientific/Engineering :: Artificial Intelligence
Requires-Python: >=3.8
License-File: LICENSE
Dynamic: license-file
